FIDL/__init__.py
FIDL/compiler_consts.py
FIDL/decompiler_utils.py
FIDL-1.1.dist-info/LICENSE
FIDL-1.1.dist-info/METADATA
FIDL-1.1.dist-info/WHEEL
FIDL-1.1.dist-info/top_level.txt
FIDL-1.1.dist-info/RECORD
