Metadata-Version: 2.1
Name: FIDL
Version: 1.1
Summary: Wrapper for the IDA decompiler API
Home-page: https://github.com/fireeye/FIDL
Author: FireEye FLARE Team
Author-email: carlos.garcia@fireeye.com
License: MIT
Keywords: ida decompiler api vulnerability research reversing malware
Platform: UNKNOWN
Classifier: Development Status :: 4 - Beta
Classifier: License :: OSI Approved :: MIT License
Classifier: Programming Language :: Python :: 3
Classifier: Topic :: Software Development :: Disassemblers
Requires-Dist: networkx
Requires-Dist: six
Provides-Extra: dev
Requires-Dist: pytest ; extra == 'dev'
Requires-Dist: pytest-pycodestyle ; extra == 'dev'
Requires-Dist: sphinx-rtd-theme ; extra == 'dev'
